<annotation>
	<folder>nike</folder>
	<filename>a293.jpg</filename>
	<path>C:\Users\Derya\Desktop\nike\a293.jpg</path>
	<source>
		<database>Unknown</database>
	</source>
	<size>
		<width>750</width>
		<height>563</height>
		<depth>3</depth>
	</size>
	<segmented>0</segmented>
	<object>
		<name>nike</name>
		<pose>Unspecified</pose>
		<truncated>0</truncated>
		<difficult>0</difficult>
		<bndbox>
			<xmin>262</xmin>
			<ymin>317</ymin>
			<xmax>337</xmax>
			<ymax>395</ymax>
		</bndbox>
	</object>
	<object>
		<name>nike</name>
		<pose>Unspecified</pose>
		<truncated>0</truncated>
		<difficult>0</difficult>
		<bndbox>
			<xmin>392</xmin>
			<ymin>294</ymin>
			<xmax>452</xmax>
			<ymax>329</ymax>
		</bndbox>
	</object>
</annotation>
