<annotation>
	<folder>new1</folder>
	<filename>a456.jpg</filename>
	<path>C:\Users\TheGodFather\Desktop\new1\a456.jpg</path>
	<source>
		<database>Unknown</database>
	</source>
	<size>
		<width>600</width>
		<height>338</height>
		<depth>3</depth>
	</size>
	<segmented>0</segmented>
	<object>
		<name>nike</name>
		<pose>Unspecified</pose>
		<truncated>0</truncated>
		<difficult>0</difficult>
		<bndbox>
			<xmin>386</xmin>
			<ymin>113</ymin>
			<xmax>457</xmax>
			<ymax>143</ymax>
		</bndbox>
	</object>
</annotation>
