<annotation>
	<folder>audi</folder>
	<filename>audi124.jpg</filename>
	<path>C:\Users\TheGodFather\Desktop\audi\audi124.jpg</path>
	<source>
		<database>Unknown</database>
	</source>
	<size>
		<width>640</width>
		<height>360</height>
		<depth>3</depth>
	</size>
	<segmented>0</segmented>
	<object>
		<name>audi</name>
		<pose>Unspecified</pose>
		<truncated>0</truncated>
		<difficult>0</difficult>
		<bndbox>
			<xmin>233</xmin>
			<ymin>146</ymin>
			<xmax>339</xmax>
			<ymax>193</ymax>
		</bndbox>
	</object>
</annotation>
