<annotation>
	<folder>audi</folder>
	<filename>audi138.jpg</filename>
	<path>C:\Users\TheGodFather\Desktop\audi\audi138.jpg</path>
	<source>
		<database>Unknown</database>
	</source>
	<size>
		<width>225</width>
		<height>225</height>
		<depth>3</depth>
	</size>
	<segmented>0</segmented>
	<object>
		<name>audi</name>
		<pose>Unspecified</pose>
		<truncated>0</truncated>
		<difficult>0</difficult>
		<bndbox>
			<xmin>93</xmin>
			<ymin>125</ymin>
			<xmax>135</xmax>
			<ymax>144</ymax>
		</bndbox>
	</object>
</annotation>
